{
  "ticker": "ALNY",
  "fetched": "2026-07-05T14:14:09.924Z",
  "source": "yahoo",
  "currency": "USD",
  "data": [
    {
      "date": "2026-05-21",
      "close": 300.51
    },
    {
      "date": "2026-05-22",
      "close": 297.45
    },
    {
      "date": "2026-05-26",
      "close": 295.5
    },
    {
      "date": "2026-05-27",
      "close": 295.63
    },
    {
      "date": "2026-05-28",
      "close": 305.06
    },
    {
      "date": "2026-05-29",
      "close": 301.98
    },
    {
      "date": "2026-06-01",
      "close": 295.63
    },
    {
      "date": "2026-06-02",
      "close": 286.12
    },
    {
      "date": "2026-06-03",
      "close": 292.58
    },
    {
      "date": "2026-06-04",
      "close": 303.64
    },
    {
      "date": "2026-06-05",
      "close": 303.05
    },
    {
      "date": "2026-06-08",
      "close": 292.16
    },
    {
      "date": "2026-06-09",
      "close": 297.69
    },
    {
      "date": "2026-06-10",
      "close": 291.22
    },
    {
      "date": "2026-06-11",
      "close": 289.39
    },
    {
      "date": "2026-06-12",
      "close": 282.85
    },
    {
      "date": "2026-06-15",
      "close": 287.8
    },
    {
      "date": "2026-06-16",
      "close": 281.9
    },
    {
      "date": "2026-06-17",
      "close": 282.72
    },
    {
      "date": "2026-06-18",
      "close": 278.09
    },
    {
      "date": "2026-06-22",
      "close": 286.41
    },
    {
      "date": "2026-06-23",
      "close": 288.18
    },
    {
      "date": "2026-06-24",
      "close": 294.06
    },
    {
      "date": "2026-06-25",
      "close": 293.17
    },
    {
      "date": "2026-06-26",
      "close": 291.37
    },
    {
      "date": "2026-06-29",
      "close": 293.52
    },
    {
      "date": "2026-06-30",
      "close": 301.03
    },
    {
      "date": "2026-07-01",
      "close": 301.67
    },
    {
      "date": "2026-07-02",
      "close": 312.78
    }
  ]
}