{
  "ticker": "IMTX",
  "fetched": "2026-05-31T02:06:41.820Z",
  "source": "yahoo",
  "currency": "USD",
  "data": [
    {
      "date": "2026-04-17",
      "close": 11.17
    },
    {
      "date": "2026-04-20",
      "close": 11.25
    },
    {
      "date": "2026-04-21",
      "close": 11.18
    },
    {
      "date": "2026-04-22",
      "close": 11.26
    },
    {
      "date": "2026-04-23",
      "close": 11.15
    },
    {
      "date": "2026-04-24",
      "close": 11.35
    },
    {
      "date": "2026-04-27",
      "close": 11.35
    },
    {
      "date": "2026-04-28",
      "close": 11.59
    },
    {
      "date": "2026-04-29",
      "close": 11.2
    },
    {
      "date": "2026-04-30",
      "close": 10.99
    },
    {
      "date": "2026-05-01",
      "close": 10.79
    },
    {
      "date": "2026-05-04",
      "close": 11.14
    },
    {
      "date": "2026-05-05",
      "close": 10.95
    },
    {
      "date": "2026-05-06",
      "close": 11.51
    },
    {
      "date": "2026-05-07",
      "close": 11.14
    },
    {
      "date": "2026-05-08",
      "close": 11.37
    },
    {
      "date": "2026-05-11",
      "close": 11.54
    },
    {
      "date": "2026-05-12",
      "close": 11.39
    },
    {
      "date": "2026-05-13",
      "close": 10.79
    },
    {
      "date": "2026-05-14",
      "close": 11.17
    },
    {
      "date": "2026-05-15",
      "close": 10.87
    },
    {
      "date": "2026-05-18",
      "close": 10.62
    },
    {
      "date": "2026-05-19",
      "close": 10.7
    },
    {
      "date": "2026-05-20",
      "close": 11.22
    },
    {
      "date": "2026-05-21",
      "close": 11.06
    },
    {
      "date": "2026-05-22",
      "close": 11.62
    },
    {
      "date": "2026-05-26",
      "close": 11.19
    },
    {
      "date": "2026-05-27",
      "close": 11.39
    },
    {
      "date": "2026-05-28",
      "close": 11.45
    },
    {
      "date": "2026-05-29",
      "close": 11.51
    }
  ]
}